oxius/__init__.py
oxius/__version__.py
oxius/cache.py
oxius/client.py
oxius/exceptions.py
oxius/response.py
oxius/utils.py
oxius-1.0.3.dist-info/licenses/LICENSE
oxius-1.0.3.dist-info/METADATA
oxius-1.0.3.dist-info/WHEEL
oxius-1.0.3.dist-info/top_level.txt
oxius-1.0.3.dist-info/RECORD
