Metadata-Version: 2.4
Name: oxius
Version: 1.0.3
Summary: Async FastAPI-style wrapper
Home-page: https://github.com/nitrix4ly/oxius
Author: Nitrix
Author-email: nitrixexe@outlook.com
Classifier: Programming Language :: Python :: 3
Classifier: License :: OSI Approved :: MIT License
Requires-Python: >=3.7
License-File: LICENSE
Dynamic: author
Dynamic: author-email
Dynamic: classifier
Dynamic: description
Dynamic: description-content-type
Dynamic: home-page
Dynamic: license-file
Dynamic: requires-python
Dynamic: summary
